GA/__init__.py
GA/filter.py
GA/floatmath.py
GA/geometry.py
GA/handlexml.py
GA/ognrequest.py
GA/output.py
GA/settings.py
eliservices_ga-0.1.0.dist-info/METADATA
eliservices_ga-0.1.0.dist-info/WHEEL
eliservices_ga-0.1.0.dist-info/top_level.txt
eliservices_ga-0.1.0.dist-info/RECORD
